shipp/__init__.py
shipp/components.py
shipp/io_functions.py
shipp/kernel.py
shipp/kernel_pyomo.py
shipp/timeseries.py
shipp-1.1.dist-info/licenses/LICENSE
shipp-1.1.dist-info/METADATA
shipp-1.1.dist-info/WHEEL
shipp-1.1.dist-info/top_level.txt
shipp-1.1.dist-info/RECORD
