Metadata-Version: 2.4
Name: shipp
Version: 1.1
Summary: A design optimization software for hybrid power plants
Author: Jenna Iori
Author-email: Jenna Iori <j.iori@tudelft.nl>
Maintainer-email: Jenna Iori <j.iori@tudelft.nl>
License: Copyright 2024-2025 Jenna Iori
Project-URL: Homepage, https://github.com/jennaiori/shipp
Project-URL: Source, https://github.com/jennaiori/shipp
Keywords: hybrid power plants,renewable energy,sizing optimization,solar energy,storage sizing,wind energy,wind farm,wind power
Classifier: Development Status :: 3 - Alpha
Classifier: Intended Audience :: Developers
Classifier: Intended Audience :: Science/Research
Classifier: Topic :: Scientific/Engineering
Classifier: License :: OSI Approved :: Apache Software License
Classifier: Programming Language :: Python :: 3
Classifier: Programming Language :: Python :: 3.9
Classifier: Programming Language :: Python :: 3.10
Classifier: Programming Language :: Python :: 3.12
Classifier: Programming Language :: Python :: 3 :: Only
Requires-Python: >=3.9
License-File: LICENSE
Requires-Dist: numpy
Requires-Dist: numpy-financial
Requires-Dist: pandas>=2.0
Requires-Dist: scipy
Requires-Dist: matplotlib
Requires-Dist: requests
Requires-Dist: pyomo
Requires-Dist: entsoe-py
Provides-Extra: dev
Requires-Dist: pytest; extra == "dev"
Dynamic: author
Dynamic: license-file
